{
    "configurations": [
        {
            "name": "Mac",
            "includePath": [
                "/usr/include",
                "/Users/jacob/Dropbox/School/CSCE5620/kubos/kubos/freertos/os/FreeRTOS/Source/include",
                "/Users/jacob/Dropbox/School/CSCE5620/kubos/kubos/kubos-core/",
                "/Users/jacob/Dropbox/School/CSCE5620/kubos/kubos/hal/kubos-hal"
            ],
            "browse": {
                "limitSymbolsToIncludedHeaders": true,
                "databaseFilename": ""
            }
        },
        {
            "name": "Linux",
            "includePath": [
                "/usr/include"
            ],
            "browse": {
                "limitSymbolsToIncludedHeaders": true,
                "databaseFilename": ""
            }
        },
        {
            "name": "Win32",
            "includePath": [
                "c:/Program Files (x86)/Microsoft Visual Studio 14.0/VC/include"
            ],
            "browse": {
                "limitSymbolsToIncludedHeaders": true,
                "databaseFilename": ""
            }
        }
    ]
}